src/data_mem.v
module data_mem(
    input clk,
    input wr_mem,
    input [31:0] alu_out,
    input [31:0] wr_data,
    input [2:0] funct3,
    output reg [31:0] rd_data
);
    //funct3
    localparam mem_size = 1023;
    localparam LB = 3'b000;   // sb
    localparam LH = 3'b001;   // sh
    localparam LW = 3'b010;   // sw
    localparam LBU = 3'b100;
    localparam LHU = 3'b101;

    reg [7:0]mem [0:mem_size];    // 1024x8 = 1KB, byte addressable

    wire [9:0]addr = alu_out[9:0];

    always @(*) begin
        case(funct3)
            LB: rd_data = {{24{mem[addr][7]}}, mem[addr]};                          //byte
            LBU: rd_data = {24'b0, mem[addr]}; 
            LH: rd_data = {{16{mem[addr+1][7]}}, mem[addr+1], mem[addr]};           //half
            LHU: rd_data = {16'b0, mem[addr+1], mem[addr]};
            LW: rd_data = {mem[addr+3], mem[addr+2], mem[addr+1], mem[addr]};       //full word for last address + 1 th instruction it is fetched from the starting address
            default: rd_data = {mem[addr+3], mem[addr+2], mem[addr+1], mem[addr]};   
        endcase
    end

    always@(posedge clk) begin
        if(wr_mem) begin
            case (funct3)
                LB: mem[addr] <= wr_data[7:0];
                LH: begin
                        mem[addr] <= wr_data[7:0];
                        mem[addr+1] <= wr_data[15:8];
                    end
                LW: begin
                        mem[addr] <= wr_data[7:0];
                        mem[addr+1] <= wr_data[15:8];
                        mem[addr+2] <= wr_data[23:16];
                        mem[addr+3] <= wr_data[31:24];
                    end
            endcase
        end
    end

endmodule

src/ALU.v
module alu(
    input [31:0] a,
    input [31:0] b,
    input [3:0]  alu_ctrl,
    output reg [31:0] alu_out,
    output reg zero,
    output reg less
);

    localparam SUB = 4'b0001;
    localparam ADD = 4'b0000;
    localparam AND = 4'b0010;
    localparam OR  = 4'b0011;
    localparam XOR = 4'b0100;
    localparam SLL = 4'b0101;
    localparam SRL = 4'b0110;
    localparam SRA = 4'b0111;
    localparam SLT = 4'b1000;
    localparam SLTU = 4'b1001; 
    
    always@(*) begin
        less = 1'b0;
        zero = 1'b0;
        alu_out = 32'd0;
        case(alu_ctrl)
                ADD: alu_out = a+b;
                SUB: begin
                    alu_out = a-b;
                    zero = !(a-b)?1:0;
                    end
                AND: alu_out = a&b;
                OR: alu_out = a | b;
                XOR: alu_out = a^b;
                SLL: alu_out = a<<b[4:0];
                SRL: alu_out = a>>b[4:0];
                SRA: alu_out = $signed(a)>>>b[4:0];
                SLT: begin
                    less = ($signed(a)<$signed(b));
                    alu_out = less?32'b1:32'b0;
                    end 
                SLTU: begin
                    less = (a<b);
                    alu_out = less?32'b1:32'b0;
                    end
        endcase
        zero = alu_out == 32'd0;
    end

endmodule

src/control_unit.v
module cu(
    input [6:0] funct7,
    input [2:0] funct3,
    input [6:0] opcode,

    output reg [1:0] pc_sel,
    output reg [1:0] result_sel,
    output reg wr_mem,
    output reg [3:0] alu_ctrl,
    output reg alu_sel,
    output reg a_sel,
    output reg [2:0] imm_sel,
    output reg wr_reg,

    input zero,
    input less
);

    localparam R = 7'b0110011;
    localparam I = 7'b0010011;
    localparam I_L = 7'b0000011;
    localparam I_J = 7'b1101111;
    localparam S = 7'b0100011;
    localparam B = 7'b1100011;
    localparam J = 7'b1100111;
    localparam LUI = 7'b0110111;
    localparam AUIPC = 7'b0010111;

    //ALU ctrl
    localparam ADD = 4'b0000;
    localparam SUB = 4'b0001;
    localparam AND = 4'b0010;
    localparam OR  = 4'b0011;
    localparam XOR = 4'b0100;
    localparam SLL = 4'b0101;
    localparam SRL = 4'b0110;
    localparam SRA = 4'b0111;
    localparam SLT = 4'b1000;
    localparam SLTU = 4'b1001;

    always @(*) begin
        result_sel = 2'b00;
        wr_mem = 1'b0;
        alu_ctrl = ADD;
        alu_sel = 1'b0;
        imm_sel = 3'b000;
        wr_reg = 1'b0;
        a_sel = 1'b0;

        case(opcode)
            R: begin
                wr_reg = 1'b1;
                case (funct3)
                    3'b000: alu_ctrl = (funct7 == 7'b0000000)?ADD:SUB; // add / sub
                    3'b001: alu_ctrl = SLL;       // sll
                    3'b010: alu_ctrl = SLT;       // slt
                    3'b011: alu_ctrl = SLTU;      // sltu
                    3'b100: alu_ctrl = XOR;       // xor
                    3'b101: alu_ctrl = (funct7 == 7'b0000000)?SRL:SRA; // srl / sra
                    3'b110: alu_ctrl = OR;        // or
                    3'b111: alu_ctrl = AND;       // and
                    default: alu_ctrl = ADD;
                endcase
            end

            I: begin
                alu_sel = 1'b1;
                wr_reg = 1'b1;
                case (funct3)
                    3'b000: alu_ctrl = ADD;       // addi
                    3'b001: alu_ctrl = SLL;       // slli
                    3'b010: alu_ctrl = SLT;       // slti
                    3'b011: alu_ctrl = SLTU;      // sltiu
                    3'b100: alu_ctrl = XOR;       // xori
                    3'b101: alu_ctrl = (funct7 == 7'b0000000)?SRL:SRA; // srli / srai
                    3'b110: alu_ctrl = OR;        // ori
                    3'b111: alu_ctrl = AND;       // andi
                    default: alu_ctrl = ADD;
                endcase
            end

            I_L: begin // load
                result_sel = 2'b01;
                alu_sel = 1'b1;
                wr_reg = 1'b1;
                alu_ctrl = ADD;
            end

            I_J: begin // jal
                imm_sel = 3'b011;
                alu_sel = 1'b1;
                wr_reg = 1'b1;
                result_sel = 2'b10;
            end

            S: begin // store
                wr_mem = 1'b1;
                alu_sel = 1'b1;
                imm_sel = 3'b001;
                alu_ctrl = ADD;
            end

            B: begin // only pick the ALU compare operation here
                imm_sel = 3'b010;
                case(funct3)
                    3'b000: alu_ctrl = SUB;   // beq
                    3'b001: alu_ctrl = SUB;   // bne
                    3'b100: alu_ctrl = SLT;   // blt
                    3'b101: alu_ctrl = SLT;   // bge
                    3'b110: alu_ctrl = SLTU;  // bltu
                    3'b111: alu_ctrl = SLTU;  // bgeu
                    default: alu_ctrl = SUB;
                endcase
            end

            J: begin // jalr
                alu_sel = 1'b1;
                wr_reg = 1'b1;
                result_sel = 2'b10;
            end

            LUI: begin
                result_sel = 2'b11;
                wr_reg = 1'b1;
                imm_sel = 3'b100;
            end

            AUIPC: begin
                imm_sel = 3'b100;
                a_sel = 1'b1;
                alu_sel = 1'b1;
                result_sel = 2'b00;
                wr_reg = 1'b1;
            end

        endcase
    end

    always @(*) begin
        pc_sel = 2'b01;
        case (opcode)
            I_J: pc_sel = 2'b00;   // jal
            J:   pc_sel = 2'b10;   // jalr
            B: begin
                case (funct3)
                    3'b000: pc_sel = zero ? 2'b00 : 2'b01;  // beq
                    3'b001: pc_sel = zero ? 2'b01 : 2'b00;  // bne
                    3'b100: pc_sel = less ? 2'b00 : 2'b01;  // blt
                    3'b101: pc_sel = less ? 2'b01 : 2'b00;  // bge
                    3'b110: pc_sel = less ? 2'b00 : 2'b01;  // bltu
                    3'b111: pc_sel = less ? 2'b01 : 2'b00;  // bgeu
                    default: pc_sel = 2'b01;
                endcase
            end
            default: pc_sel = 2'b01;
        endcase
    end

endmodule

src/immediate_gen.v
module imm_gen(
    input [31:0] instr,
    input [2:0] imm_sel,
    output reg [31:0] imm_out
);

    always@(*) begin
        case(imm_sel) 
            3'b000: imm_out = {{20{instr[31]}}, instr[31:20]};       // I 
            3'b001: imm_out = {{20{instr[31]}}, instr[31:25], instr[11:7]};      // S
            3'b010: imm_out = {{19{instr[31]}}, instr[31], instr[7], instr[30:25], instr[11:8], 1'b0};      // B
            3'b011: imm_out = {{11{instr[31]}}, instr[31], instr[19:12], instr[20], instr[30:21], 1'b0};      // J
            3'b100: imm_out = {{instr[31:12], 12'b0}};   // U
        endcase
    end

endmodule

src/reg_mem.v
module reg_mem(

    input clk,
    input [4:0] rs1,
    input [4:0] rs2,
    output reg [31:0] rd_1,
    output reg [31:0] rd_2,
    input wr_reg,
    input [31:0] result,
    input [4:0] rd,
    input rst
    
);

    reg [31:0] registers [0:31];

    always @(*) begin
        rd_1 = registers[rs1];
        rd_2 = registers[rs2];
    end

    integer i;
    
    always @(posedge clk) begin
        if(rst) begin
            for(i = 0; i<32; i = i + 1) begin
                registers[i] <= 0;
            end
        end
        else if(wr_reg && rd != 5'd0) begin
            registers[rd] <= result;
        end
    end

endmodule

src/instruction_mem.v
module inst_mem(
    input [31:0] pc,
    output reg [31:0] inst
);

reg [31:0] mem [0:255];    // 256 x 32 = 1kb

always@(*) begin
    inst = mem[pc[9:2]];     // 2^8 = 256
end

endmodule

src/pc.v
module pc(

    input clk,
    input [31:0] pc_next, // immediate/jump 
    input rst,
    output reg [31:0] pc
);

    always@(posedge clk) begin
        if(rst) begin
            pc <= 32'd0;
        end
        else begin
            pc <= pc_next;
        end
    end

endmodule

src/mux.v
module pc_mux(
    input [1:0] pc_sel,
    input [31:0] pc,
    input [31:0] imm_out,
    input [31:0] alu_out,
    output reg [31:0] pc_next
);

    always@(*) begin
        case(pc_sel) 
            2'b01: pc_next <= pc + 4;
            2'b00: pc_next <= pc + imm_out;
            2'b10: pc_next <= alu_out;
            default: pc_next <= pc + 4;
        endcase
    end
endmodule

module alu_mux(
    input alu_sel,
    input [31:0] rd2,
    input [31:0] imm_out,
    output reg [31:0] in_alu
);

    always@(*) begin
        in_alu = alu_sel?(imm_out):(rd2);
    end

endmodule

// module result_mux(
//     input result_sel,
//     input [31:0] alu_out,
//     input [31:0] rd_data,
//     output reg [31:0] result
// );

//     always@(*) begin
//         result = result_sel?(rd_data):(alu_out);
//     end

// endmodule

module result_mux(
    input [1:0] result_sel,
    input [31:0] alu_out,
    input [31:0] rd_data,
    input [31:0] pc_plus4,
    input [31:0] imm_out,
    output reg [31:0] result
);
    always@(*) begin
        case (result_sel)
            2'b00: result = alu_out;    // r,i,alu,auipc
            2'b01: result = rd_data;    // load
            2'b10: result = pc_plus4;   // jal or jalr link address
            2'b11: result = imm_out;    // LUI
            default: result = alu_out;
        endcase
    end
endmodule

module alu_a_mux(
    input a_sel,
    input [31:0] rd1,
    input [31:0] pc,
    output reg [31:0] in_a
);
    always@(*) begin
        in_a = a_sel?pc:rd1;
    end
endmodule

src/top.v
`include "mux.v"

module top(
    input clk,
    input rst
);
    // pc
    wire [31:0] pc_next;
    wire [1:0] pc_sel;
    wire [31:0] pc;

    // instruction memory
    wire [31:0] instr;
    wire [4:0] rs1 = instr[19:15];
    wire [4:0] rs2 = instr[24:20];
    wire [4:0] rd = instr[11:7];

    // alu
    wire [31:0] rd1;
    wire [31:0] rd2;
    wire [3:0] alu_ctrl;
    wire [31:0] alu_out;
    wire zero;
    wire less;
    wire [31:0] alu_in;

    // immediate generator
    wire [2:0] imm_sel;
    wire [31:0] imm_out;
    
    // control signals & result
    wire a_sel;
    wire [31:0] alu_a;
    wire [31:0] pc_plus4 = pc + 32'd4;
    wire [1:0] result_sel;
    wire [31:0] result;
    wire wr_mem;
    wire alu_sel;
    wire wr_reg;
    wire [2:0] funct3 = instr[14:12];
    wire [6:0] funct7 = instr[31:25];
    wire [6:0] opcode = instr[6:0];
    wire [31:0] rd_data;

    pc_mux pmux(
        .pc_sel(pc_sel),
        .pc(pc),
        .imm_out(imm_out),
        .alu_out(alu_out),
        .pc_next(pc_next)
    );

    alu_a_mux alu_amux(
        .a_sel(a_sel),
        .rd1(rd1),
        .pc(pc),
        .in_a(alu_a)
    );

    alu_mux alumux(
        .alu_sel(alu_sel),
        .rd2(rd2),
        .imm_out(imm_out),
        .in_alu(alu_in)
    );

    result_mux resultmux(
        .result_sel(result_sel),
        .alu_out(alu_out),
        .rd_data(rd_data),
        .pc_plus4(pc_plus4),
        .imm_out(imm_out),
        .result(result)
    );

    pc inst1(
        .clk(clk),
        .pc_next(pc_next),
        .rst(rst),
        .pc(pc)
    );

    inst_mem inst2(
        .pc(pc),
        .inst(instr)
    );

    reg_mem inst3(
        .clk(clk),
        .rs1(rs1),
        .rs2(rs2),
        .rd_1(rd1),
        .rd_2(rd2),
        .wr_reg(wr_reg),
        .result(result),
        .rd(rd),
        .rst(rst)
    );

    imm_gen inst4(
        .instr(instr),
        .imm_sel(imm_sel),
        .imm_out(imm_out)
    );

    cu inst5(
        .a_sel(a_sel),
        .funct7(funct7),
        .funct3(funct3),
        .opcode(opcode),
        .pc_sel(pc_sel),
        .result_sel(result_sel),
        .wr_mem(wr_mem),
        .alu_ctrl(alu_ctrl),
        .alu_sel(alu_sel),
        .imm_sel(imm_sel),
        .wr_reg(wr_reg),
        .zero(zero),
        .less(less)
    );

    alu inst6(
        .a(alu_a),
        .b(alu_in),
        .alu_ctrl(alu_ctrl),
        .alu_out(alu_out),
        .zero(zero),
        .less(less)
    );

    data_mem inst7(
        .clk(clk),
        .wr_mem(wr_mem),
        .alu_out(alu_out),
        .wr_data(rd2),
        .funct3(funct3),
        .rd_data(rd_data)
    );

endmodule

src/tb2.v
`timescale 1ns/1ps

module tb2;

    reg clk = 0;
    reg rst = 1;

    top dut(.clk(clk), .rst(rst));

    always #5 clk = ~clk;

    localparam HALT = 32'h0000006f;
    localparam NOP  = 32'h00000013;
    localparam TIMEOUT = 2000;

    integer pass = 0;
    integer fail = 0;
    integer i, cycles;

    task clear_imem;
        for (i=0; i<256; i=i+1)
            dut.inst2.mem[i] = NOP;
    endtask

    task run;
        begin
            rst = 1;
            repeat(2)@(negedge clk);
            rst = 0;

            cycles = 0;
            while(dut.instr !== HALT && cycles < TIMEOUT) begin
                @(negedge clk);
                cycles = cycles + 1;
            end

            if(cycles >= TIMEOUT)
                $display(" TIMEOUT: program never reached halt");
        end
    endtask

    task check_reg(input [4:0] r, input [31:0] exp);
        reg [31:0] got;
        begin
            got = dut.inst3.registers[r];
            if(got === exp) begin
                pass = pass + 1;
                $display(" PASS  x%0d = 0x%h", r, got);
            end
            else begin
                fail = fail + 1;
                $display(" FAIL  x%0d = 0x%h, expected 0x%h", r, got, exp);
            end
        end
    endtask

    initial begin
        $dumpfile("cpu2.vcd");
        $dumpvars(0, tb2);

        // lui
        $display("\nTEST 1: lui");
        clear_imem;
        dut.inst2.mem[0] = 32'h123450b7;   // lui  x1, 0x12345
        dut.inst2.mem[1] = 32'h67808113;   // addi x2, x1, 0x678
        dut.inst2.mem[2] = 32'hfffff1b7;   // lui  x3, 0xfffff
        dut.inst2.mem[3] = HALT;
        run;
        check_reg(1, 32'h12345000);
        check_reg(2, 32'h12345678);
        check_reg(3, 32'hfffff000);

        // auipc
        $display("\nTEST 2: auipc");
        clear_imem;
        dut.inst2.mem[0] = 32'h00000097;   // auipc x1, 0
        dut.inst2.mem[1] = 32'h00001117;   // auipc x2, 1
        dut.inst2.mem[2] = 32'hfffff197;   // auipc x3, 0xfffff
        dut.inst2.mem[3] = HALT;
        run;
        check_reg(1, 32'h00000000);        // pc = 0
        check_reg(2, 32'h00001004);        // pc = 4
        check_reg(3, 32'hfffff008);        // pc = 8

        // jalr
        $display("\nTEST 3: jalr");
        clear_imem;
        dut.inst2.mem[0] = 32'h01000093;   // addi x1, x0, 16
        dut.inst2.mem[1] = 32'h00008167;   // jalr x2, 0(x1)
        dut.inst2.mem[2] = 32'h06300193;   // addi x3, x0, 99  (skipped)
        dut.inst2.mem[3] = 32'h06300193;   // addi x3, x0, 99  (skipped)
        dut.inst2.mem[4] = 32'h00700213;   // addi x4, x0, 7
        dut.inst2.mem[5] = 32'h00c082e7;   // jalr x5, 12(x1)
        dut.inst2.mem[6] = 32'h06300313;   // addi x6, x0, 99  (skipped)
        dut.inst2.mem[7] = HALT;
        run;
        check_reg(1, 16);
        check_reg(2, 8);                   // link address of first jalr
        check_reg(3, 0);                   // skipped
        check_reg(4, 7);                   // landed on the target
        check_reg(5, 24);                  // link address of second jalr
        check_reg(6, 0);                   // skipped

        $display("\n%0d passed, %0d failed", pass, fail);
        if(fail == 0)
            $display("ALL TESTS PASSED\n");
        else
            $display("%0d TESTS FAILED\n", fail);
        $finish;
    end

endmodule

src/cpu2.vcd
$date
	Tue Oct  6 14:43:24 2026
$end
$version
	Icarus Verilog
$end
$timescale
	1ps
$end
$scope module tb2 $end
$var parameter 32 ! HALT $end
$var parameter 32 " NOP $end
$var parameter 32 # TIMEOUT $end
$var reg 1 $ clk $end
$var reg 1 % rst $end
$var integer 32 & cycles [31:0] $end
$var integer 32 ' fail [31:0] $end
$var integer 32 ( i [31:0] $end
$var integer 32 ) pass [31:0] $end
$scope module dut $end
$var wire 1 $ clk $end
$var wire 1 % rst $end
$var wire 1 * zero $end
$var wire 1 + wr_reg $end
$var wire 1 , wr_mem $end
$var wire 5 - rs2 [4:0] $end
$var wire 5 . rs1 [4:0] $end
$var wire 2 / result_sel [1:0] $end
$var wire 32 0 result [31:0] $end
$var wire 32 1 rd_data [31:0] $end
$var wire 32 2 rd2 [31:0] $end
$var wire 32 3 rd1 [31:0] $end
$var wire 5 4 rd [4:0] $end
$var wire 2 5 pc_sel [1:0] $end
$var wire 32 6 pc_plus4 [31:0] $end
$var wire 32 7 pc_next [31:0] $end
$var wire 32 8 pc [31:0] $end
$var wire 7 9 opcode [6:0] $end
$var wire 1 : less $end
$var wire 32 ; instr [31:0] $end
$var wire 3 < imm_sel [2:0] $end
$var wire 32 = imm_out [31:0] $end
$var wire 7 > funct7 [6:0] $end
$var wire 3 ? funct3 [2:0] $end
$var wire 1 @ alu_sel $end
$var wire 32 A alu_out [31:0] $end
$var wire 32 B alu_in [31:0] $end
$var wire 4 C alu_ctrl [3:0] $end
$var wire 32 D alu_a [31:0] $end
$var wire 1 E a_sel $end
$scope module alu_amux $end
$var wire 32 F rd1 [31:0] $end
$var wire 32 G pc [31:0] $end
$var wire 1 E a_sel $end
$var reg 32 H in_a [31:0] $end
$upscope $end
$scope module alumux $end
$var wire 32 I rd2 [31:0] $end
$var wire 32 J imm_out [31:0] $end
$var wire 1 @ alu_sel $end
$var reg 32 K in_alu [31:0] $end
$upscope $end
$scope module inst1 $end
$var wire 1 $ clk $end
$var wire 1 % rst $end
$var wire 32 L pc_next [31:0] $end
$var reg 32 M pc [31:0] $end
$upscope $end
$scope module inst2 $end
$var wire 32 N pc [31:0] $end
$var reg 32 O inst [31:0] $end
$upscope $end
$scope module inst3 $end
$var wire 1 $ clk $end
$var wire 5 P rd [4:0] $end
$var wire 5 Q rs1 [4:0] $end
$var wire 5 R rs2 [4:0] $end
$var wire 1 % rst $end
$var wire 1 + wr_reg $end
$var wire 32 S result [31:0] $end
$var reg 32 T rd_1 [31:0] $end
$var reg 32 U rd_2 [31:0] $end
$var integer 32 V i [31:0] $end
$upscope $end
$scope module inst4 $end
$var wire 32 W instr [31:0] $end
$var wire 3 X imm_sel [2:0] $end
$var reg 32 Y imm_out [31:0] $end
$upscope $end
$scope module inst5 $end
$var wire 3 Z funct3 [2:0] $end
$var wire 7 [ funct7 [6:0] $end
$var wire 7 \ opcode [6:0] $end
$var wire 1 * zero $end
$var wire 1 : less $end
$var parameter 4 ] ADD $end
$var parameter 4 ^ AND $end
$var parameter 7 _ AUIPC $end
$var parameter 7 ` B $end
$var parameter 7 a I $end
$var parameter 7 b I_J $end
$var parameter 7 c I_L $end
$var parameter 7 d J $end
$var parameter 7 e LUI $end
$var parameter 4 f OR $end
$var parameter 7 g R $end
$var parameter 7 h S $end
$var parameter 4 i SLL $end
$var parameter 4 j SLT $end
$var parameter 4 k SLTU $end
$var parameter 4 l SRA $end
$var parameter 4 m SRL $end
$var parameter 4 n SUB $end
$var parameter 4 o XOR $end
$var reg 1 E a_sel $end
$var reg 4 p alu_ctrl [3:0] $end
$var reg 1 @ alu_sel $end
$var reg 3 q imm_sel [2:0] $end
$var reg 2 r pc_sel [1:0] $end
$var reg 2 s result_sel [1:0] $end
$var reg 1 , wr_mem $end
$var reg 1 + wr_reg $end
$upscope $end
$scope module inst6 $end
$var wire 32 t a [31:0] $end
$var wire 4 u alu_ctrl [3:0] $end
$var wire 32 v b [31:0] $end
$var parameter 4 w ADD $end
$var parameter 4 x AND $end
$var parameter 4 y OR $end
$var parameter 4 z SLL $end
$var parameter 4 { SLT $end
$var parameter 4 | SLTU $end
$var parameter 4 } SRA $end
$var parameter 4 ~ SRL $end
$var parameter 4 !" SUB $end
$var parameter 4 "" XOR $end
$var reg 32 #" alu_out [31:0] $end
$var reg 1 : less $end
$var reg 1 * zero $end
$upscope $end
$scope module inst7 $end
$var wire 32 $" alu_out [31:0] $end
$var wire 1 $ clk $end
$var wire 3 %" funct3 [2:0] $end
$var wire 32 &" wr_data [31:0] $end
$var wire 1 , wr_mem $end
$var wire 10 '" addr [9:0] $end
$var parameter 3 (" LB $end
$var parameter 3 )" LBU $end
$var parameter 3 *" LH $end
$var parameter 3 +" LHU $end
$var parameter 3 ," LW $end
$var parameter 32 -" mem_size $end
$var reg 32 ." rd_data [31:0] $end
$upscope $end
$scope module pmux $end
$var wire 32 /" alu_out [31:0] $end
$var wire 32 0" imm_out [31:0] $end
$var wire 32 1" pc [31:0] $end
$var wire 2 2" pc_sel [1:0] $end
$var reg 32 3" pc_next [31:0] $end
$upscope $end
$scope module resultmux $end
$var wire 32 4" alu_out [31:0] $end
$var wire 32 5" imm_out [31:0] $end
$var wire 32 6" pc_plus4 [31:0] $end
$var wire 32 7" rd_data [31:0] $end
$var wire 2 8" result_sel [1:0] $end
$var reg 32 9" result [31:0] $end
$upscope $end
$upscope $end
$scope task check_reg $end
$var reg 32 :" exp [31:0] $end
$var reg 32 ;" got [31:0] $end
$var reg 5 <" r [4:0] $end
$upscope $end
$scope task clear_imem $end
$upscope $end
$scope task run $end
$upscope $end
$upscope $end
$enddefinitions $end
$comment Show the parameter values. $end
$dumpall
b1111111111 -"
b10 ,"
b101 +"
b1 *"
b100 )"
b0 ("
b100 ""
b1 !"
b110 ~
b111 }
b1001 |
b1000 {
b101 z
b11 y
b10 x
b0 w
b100 o
b1 n
b110 m
b111 l
b1001 k
b1000 j
b101 i
b100011 h
b110011 g
b11 f
b110111 e
b1100111 d
b11 c
b1101111 b
b10011 a
b1100011 `
b10111 _
b10 ^
b0 ]
b11111010000 #
b10011 "
b1101111 !
$end
#0
$dumpvars
bx <"
bx ;"
bx :"
bx 9"
bx 8"
bx 7"
bx 6"
bx 5"
bx 4"
bx 3"
bx 2"
bx 1"
bx 0"
bx /"
bx ."
bx '"
bx &"
bx %"
bx $"
bx #"
bx v
bx u
bx t
bx s
bx r
bx q
bx p
bx \
bx [
bx Z
bx Y
bx X
bx W
bx V
bx U
bx T
bx S
bx R
bx Q
bx P
bx O
bx N
bx M
bx L
bx K
bx J
bx I
bx H
bx G
bx F
xE
bx D
bx C
bx B
bx A
x@
bx ?
bx >
bx =
bx <
bx ;
x:
bx 9
bx 8
bx 7
bx 6
bx 5
bx 4
bx 3
bx 2
bx 1
bx 0
bx /
bx .
bx -
x,
x+
x*
b0 )
b100000000 (
b0 '
bx &
1%
0$
$end
#5000
b0 '"
b10010001101000101000000000000 0
b10010001101000101000000000000 S
b10010001101000101000000000000 9"
b10010001101000101000000000000 =
b10010001101000101000000000000 J
b10010001101000101000000000000 Y
b10010001101000101000000000000 0"
b10010001101000101000000000000 5"
b0 A
b0 #"
b0 $"
b0 /"
b0 4"
1*
0:
b0 B
b0 K
b0 v
b0 D
b0 H
b0 t
b1 5
b1 r
b1 2"
0E
1+
b100 <
b100 X
b100 q
0@
b0 C
b0 p
b0 u
0,
b11 /
b11 s
b11 8"
b0xxxxxxxxxxxxxxxx 1
b0xxxxxxxxxxxxxxxx ."
b0xxxxxxxxxxxxxxxx 7"
b0 2
b0 I
b0 U
b0 &"
b0 3
b0 F
b0 T
b110111 9
b110111 \
b1001 >
b1001 [
b101 ?
b101 Z
b101 %"
b1 4
b1 P
b11 -
b11 R
b1000 .
b1000 Q
b10010001101000101000010110111 ;
b10010001101000101000010110111 O
b10010001101000101000010110111 W
b100 7
b100 L
b100 3"
b100 6
b100 6"
b0 8
b0 G
b0 M
b0 N
b0 1"
b100000 V
1$
#10000
0$
#15000
b100000 V
1$
#20000
b0 &
0%
0$
#25000
b1001111000 '"
b10010001101000101011001111000 A
b10010001101000101011001111000 #"
b10010001101000101011001111000 $"
b10010001101000101011001111000 /"
b10010001101000101011001111000 4"
0*
b10010001101000101000000000000 D
b10010001101000101000000000000 H
b10010001101000101000000000000 t
b11001111000 B
b11001111000 K
b11001111000 v
b10010001101000101011001111000 0
b10010001101000101011001111000 S
b10010001101000101011001111000 9"
1@
1+
b0 <
b0 X
b0 q
b0 /
b0 s
b0 8"
bx 1
bx ."
bx 7"
b10010001101000101000000000000 3
b10010001101000101000000000000 F
b10010001101000101000000000000 T
b11001111000 =
b11001111000 J
b11001111000 Y
b11001111000 0"
b11001111000 5"
b10011 9
b10011 \
b110011 >
b110011 [
b0 ?
b0 Z
b0 %"
b10 4
b10 P
b11000 -
b11000 R
b1 .
b1 Q
b1100111100000001000000100010011 ;
b1100111100000001000000100010011 O
b1100111100000001000000100010011 W
b1000 7
b1000 L
b1000 3"
b1000 6
b1000 6"
b100 8
b100 G
b100 M
b100 N
b100 1"
1$
#30000
b1 &
0$
#35000
b0 '"
1*
b0 A
b0 #"
b0 $"
b0 /"
b0 4"
b0 D
b0 H
b0 t
b0 B
b0 K
b0 v
b11111111111111111111000000000000 0
b11111111111111111111000000000000 S
b11111111111111111111000000000000 9"
b100 <
b100 X
b100 q
b11 /
b11 s
b11 8"
1+
0@
b0 3
b0 F
b0 T
b11111111111111111111000000000000 =
b11111111111111111111000000000000 J
b11111111111111111111000000000000 Y
b11111111111111111111000000000000 0"
b11111111111111111111000000000000 5"
b110111 9
b110111 \
b1111111 >
b1111111 [
b111 ?
b111 Z
b111 %"
b11 4
b11 P
b11111 -
b11111 R
b11111 .
b11111 Q
b11111111111111111111000110110111 ;
b11111111111111111111000110110111 O
b11111111111111111111000110110111 W
b1100 7
b1100 L
b1100 3"
b1100 6
b1100 6"
b1000 8
b1000 G
b1000 M
b1000 N
b1000 1"
1$
#40000
b10 &
0$
#45000
b10000 0
b10000 S
b10000 9"
b0 5
b0 r
b0 2"
1@
1+
b11 <
b11 X
b11 q
b10 /
b10 s
b10 8"
b0 =
b0 J
b0 Y
b0 0"
b0 5"
b1101111 9
b1101111 \
b0 >
b0 [
b0 ?
b0 Z
b0 %"
b0 4
b0 P
b0 -
b0 R
b0 .
b0 Q
b1101111 ;
b1101111 O
b1101111 W
b1100 7
b1100 L
b1100 3"
b10000 6
b10000 6"
b1100 8
b1100 G
b1100 M
b1100 N
b1100 1"
1$
#50000
1%
b100000000 (
b11 )
b11111111111111111111000000000000 ;"
b11111111111111111111000000000000 :"
b11 <"
b11 &
0$
#55000
b1 5
b1 r
b1 2"
1E
1+
b100 <
b100 X
b100 q
1@
b0 /
b0 s
b0 8"
b10111 9
b10111 \
b1 4
b1 P
b0 0
b0 S
b0 9"
b10010111 ;
b10010111 O
b10010111 W
b100 7
b100 L
b100 3"
b100 6
b100 6"
b0 8
b0 G
b0 M
b0 N
b0 1"
b100000 V
1$
#60000
0$
#65000
b100000 V
1$
#70000
b0 &
0%
0$
#75000
b100 '"
b1000000000000 B
b1000000000000 K
b1000000000000 v
b1000000000100 0
b1000000000100 S
b1000000000100 9"
1E
1+
b100 <
b100 X
b100 q
1@
b1000000000100 A
b1000000000100 #"
b1000000000100 $"
b1000000000100 /"
b1000000000100 4"
0*
b1000000000000 =
b1000000000000 J
b1000000000000 Y
b1000000000000 0"
b1000000000000 5"
b1 ?
b1 Z
b1 %"
b10 4
b10 P
b100 D
b100 H
b100 t
b1000100010111 ;
b1000100010111 O
b1000100010111 W
b1000 7
b1000 L
b1000 3"
b1000 6
b1000 6"
b100 8
b100 G
b100 M
b100 N
b100 1"
1$
#80000
b1 &
0$
#85000
b1000 '"
b11111111111111111111000000000000 B
b11111111111111111111000000000000 K
b11111111111111111111000000000000 v
b11111111111111111111000000001000 0
b11111111111111111111000000001000 S
b11111111111111111111000000001000 9"
1E
1+
b100 <
b100 X
b100 q
1@
b11111111111111111111000000001000 A
b11111111111111111111000000001000 #"
b11111111111111111111000000001000 $"
b11111111111111111111000000001000 /"
b11111111111111111111000000001000 4"
b11111111111111111111000000000000 =
b11111111111111111111000000000000 J
b11111111111111111111000000000000 Y
b11111111111111111111000000000000 0"
b11111111111111111111000000000000 5"
b1111111 >
b1111111 [
b111 ?
b111 Z
b111 %"
b11 4
b11 P
b11111 -
b11111 R
b11111 .
b11111 Q
b1000 D
b1000 H
b1000 t
b11111111111111111111000110010111 ;
b11111111111111111111000110010111 O
b11111111111111111111000110010111 W
b1100 7
b1100 L
b1100 3"
b1100 6
b1100 6"
b1000 8
b1000 G
b1000 M
b1000 N
b1000 1"
1$
#90000
b10 &
0$
#95000
1*
b0 '"
b0 B
b0 K
b0 v
b10000 0
b10000 S
b10000 9"
b0 5
b0 r
b0 2"
b10 /
b10 s
b10 8"
0E
1+
b11 <
b11 X
b11 q
1@
b0 A
b0 #"
b0 $"
b0 /"
b0 4"
b0 =
b0 J
b0 Y
b0 0"
b0 5"
b1101111 9
b1101111 \
b0 >
b0 [
b0 ?
b0 Z
b0 %"
b0 4
b0 P
b0 -
b0 R
b0 .
b0 Q
b0 D
b0 H
b0 t
b1101111 ;
b1101111 O
b1101111 W
b1100 7
b1100 L
b1100 3"
b10000 6
b10000 6"
b1100 8
b1100 G
b1100 M
b1100 N
b1100 1"
1$
